{
    "acquisition_software": "pychron py3/18.2",
    "aliquot": 1753,
    "analysis_type": "air",
    "analyst_name": "",
    "arar_mapping": {
        "Ar36": "Ar36",
        "Ar37": "Ar37",
        "Ar38": "Ar38",
        "Ar39": "Ar39",
        "Ar40": "Ar40"
    },
    "collection_version": "1.0:2.0",
    "comment": "",
    "commit": "f3b1e278a55b9bf8453b5550bc23e55b6dba2468",
    "conditionals": [
        {
            "analysis_types": [],
            "frequency": 10,
            "hash_id": 1357203645798028354,
            "level": 10,
            "location": "setupfiles/spectrometer/default_conditionals.yaml",
            "ntrips": 1,
            "start_count": 5,
            "teststr": "L2(CDD).deflection==3250"
        }
    ],
    "data_reduction_software": "pychron py3/18.2",
    "detectors": {
        "AX": {
            "deflection": 0.0,
            "gain": 1
        },
        "H1": {
            "deflection": 0.0,
            "gain": 1
        },
        "H2": {
            "deflection": 0.0,
            "gain": 1
        },
        "L1": {
            "deflection": 0.0,
            "gain": 1
        },
        "L2(CDD)": {
            "deflection": 0.0,
            "gain": 1
        }
    },
    "environmental": {
        "lab_humiditys": [
            {
                "device": "EnvironmentalMonitor",
                "name": "Lab Hum.",
                "pub_date": "2019-02-27T04:48:53",
                "title": "iServer Hum.",
                "value": 18.2
            }
        ],
        "lab_pneumatics": [
            {
                "device": "AirPressure",
                "name": "Pressure",
                "pub_date": "2019-02-26T20:18:44",
                "title": "Building",
                "value": 101.0
            },
            {
                "device": "AirPressure2",
                "name": "Pressure2",
                "pub_date": "2019-02-26T16:33:20",
                "title": "Lab",
                "value": 87.9
            }
        ],
        "lab_temperatures": []
    },
    "experiment_queue_name": "LoadLF0001",
    "experiment_type": "Ar/Ar",
    "extraction": "felix_air_x1.py",
    "grainsize": "",
    "identifier": "a-02-F",
    "increment": null,
    "instrument_name": "",
    "intensity_scalar": 0.0,
    "irradiation": "NoIrradiation",
    "irradiation_level": "A",
    "irradiation_position": 17,
    "isotopes": {
        "Ar36": {
            "detector": "L2(CDD)",
            "name": "Ar36",
            "serial_id": "00000"
        },
        "Ar37": {
            "detector": "L1",
            "name": "Ar37",
            "serial_id": "00000"
        },
        "Ar38": {
            "detector": "AX",
            "name": "Ar38",
            "serial_id": "00000"
        },
        "Ar39": {
            "detector": "H1",
            "name": "Ar39",
            "serial_id": "00000"
        },
        "Ar40": {
            "detector": "H2",
            "name": "Ar40",
            "serial_id": "00000"
        }
    },
    "laboratory": "",
    "latitude": null,
    "lithology": null,
    "lithology_class": null,
    "lithology_group": null,
    "lithology_type": null,
    "longitude": null,
    "mass_spectrometer": "felix",
    "material": "Gas",
    "measurement": "felix_analysis340_60_CDD_center.py",
    "post_equilibration": "felix_pump_extraction_line.py",
    "post_measurement": "felix_pump_ms.py",
    "principal_investigator": "NMGRL",
    "project": "REFERENCES",
    "queue_conditionals_name": "",
    "repository_identifier": "Felix_air190",
    "rlocation": "",
    "sample": "air",
    "source": {
        "emission": 781.118,
        "trap": 249.054
    },
    "spec_sha": "95b25b5441837ae5a8124d43315d63cbf6b5733c",
    "timestamp": "2019-02-27T14:47:12.208444",
    "tripped_conditional": null,
    "username": "",
    "uuid": "95db4c2f-d628-40f0-b1be-a061adef768c",
    "whiff_result": null
}